triodia
