Metadata-Version: 1.1
Name: django-triodia
Version: 0.1
Summary: A Django app to check taxonomic species names against web based data services such as GBIF.
Home-page: http://www.example.com/
Author: Chid Gilovitz
Author-email: chid@chidgilovitz.com
License: MIT License
Platform: UNKNOWN
Classifier: Environment :: Web Environment
Classifier: Framework :: Django
Classifier: Intended Audience :: Developers
Classifier: License :: OSI Approved :: MIT License
Classifier: Operating System :: OS Independent
Classifier: Programming Language :: Python
Classifier: Programming Language :: Python :: 2.6
Classifier: Programming Language :: Python :: 2.7
Classifier: Topic :: Internet :: WWW/HTTP
Classifier: Topic :: Internet :: WWW/HTTP :: Dynamic Content
